LICENSE.txt
MANIFEST.in
README.rst
requirements.txt
setup.py
yaclifw/RELEASE-VERSION
yaclifw/__init__.py
yaclifw/example.py
yaclifw/framework.py
yaclifw/main.py
yaclifw/version.py
yaclifw.egg-info/PKG-INFO
yaclifw.egg-info/SOURCES.txt
yaclifw.egg-info/dependency_links.txt
yaclifw.egg-info/entry_points.txt
yaclifw.egg-info/not-zip-safe
yaclifw.egg-info/requires.txt
yaclifw.egg-info/top_level.txt